{
  "version": "5",
  "dialect": "mysql",
  "id": "d8136228-c789-40b3-bd86-04227bad69cd",
  "prevId": "8bbfb1dc-dd6d-42e7-9d68-25a7112cebd2",
  "tables": {
    "cadeia_contratos": {
      "name": "cadeia_contratos",
      "columns": {
        "id": {
          "name": "id",
          "type": "int",
          "primaryKey": false,
          "notNull": true,
          "autoincrement": true
        },
        "userId": {
          "name": "userId",
          "type": "int",
          "primaryKey": false,
          "notNull": true,
          "autoincrement": false
        },
        "nome": {
          "name": "nome",
          "type": "varchar(255)",
          "primaryKey": false,
          "notNull": true,
          "autoincrement": false
        },
        "banco": {
          "name": "banco",
          "type": "varchar(255)",
          "primaryKey": false,
          "notNull": true,
          "autoincrement": false
        },
        "descricao": {
          "name": "descricao",
          "type": "text",
          "primaryKey": false,
          "notNull": false,
          "autoincrement": false
        },
        "laudoGerado": {
          "name": "laudoGerado",
          "type": "text",
          "primaryKey": false,
          "notNull": false,
          "autoincrement": false
        },
        "laudoGeradoEm": {
          "name": "laudoGeradoEm",
          "type": "timestamp",
          "primaryKey": false,
          "notNull": false,
          "autoincrement": false
        },
        "createdAt": {
          "name": "createdAt",
          "type": "timestamp",
          "primaryKey": false,
          "notNull": true,
          "autoincrement": false,
          "default": "(now())"
        },
        "updatedAt": {
          "name": "updatedAt",
          "type": "timestamp",
          "primaryKey": false,
          "notNull": true,
          "autoincrement": false,
          "onUpdate": true,
          "default": "(now())"
        }
      },
      "indexes": {},
      "foreignKeys": {},
      "compositePrimaryKeys": {
        "cadeia_contratos_id": {
          "name": "cadeia_contratos_id",
          "columns": [
            "id"
          ]
        }
      },
      "uniqueConstraints": {},
      "checkConstraint": {}
    },
    "calculos_tcr": {
      "name": "calculos_tcr",
      "columns": {
        "id": {
          "name": "id",
          "type": "int",
          "primaryKey": false,
          "notNull": true,
          "autoincrement": true
        },
        "userId": {
          "name": "userId",
          "type": "int",
          "primaryKey": false,
          "notNull": false,
          "autoincrement": false
        },
        "nomeDevedor": {
          "name": "nomeDevedor",
          "type": "varchar(255)",
          "primaryKey": false,
          "notNull": false,
          "autoincrement": false
        },
        "numeroCedula": {
          "name": "numeroCedula",
          "type": "varchar(100)",
          "primaryKey": false,
          "notNull": false,
          "autoincrement": false
        },
        "modalidade": {
          "name": "modalidade",
          "type": "enum('custeio','investimento','comercializacao')",
          "primaryKey": false,
          "notNull": true,
          "autoincrement": false
        },
        "tipoTaxa": {
          "name": "tipoTaxa",
          "type": "enum('pre_fixada','pos_fixada')",
          "primaryKey": false,
          "notNull": true,
          "autoincrement": false
        },
        "valorPrincipal": {
          "name": "valorPrincipal",
          "type": "decimal(18,2)",
          "primaryKey": false,
          "notNull": true,
          "autoincrement": false
        },
        "dataContratacao": {
          "name": "dataContratacao",
          "type": "timestamp",
          "primaryKey": false,
          "notNull": true,
          "autoincrement": false
        },
        "dataVencimento": {
          "name": "dataVencimento",
          "type": "timestamp",
          "primaryKey": false,
          "notNull": true,
          "autoincrement": false
        },
        "dataCalculo": {
          "name": "dataCalculo",
          "type": "timestamp",
          "primaryKey": false,
          "notNull": true,
          "autoincrement": false
        },
        "prazoMeses": {
          "name": "prazoMeses",
          "type": "int",
          "primaryKey": false,
          "notNull": true,
          "autoincrement": false
        },
        "taxaJurosRemuneratorios": {
          "name": "taxaJurosRemuneratorios",
          "type": "decimal(8,4)",
          "primaryKey": false,
          "notNull": true,
          "autoincrement": false
        },
        "taxaJurosMora": {
          "name": "taxaJurosMora",
          "type": "decimal(8,4)",
          "primaryKey": false,
          "notNull": false,
          "autoincrement": false
        },
        "taxaMulta": {
          "name": "taxaMulta",
          "type": "decimal(8,4)",
          "primaryKey": false,
          "notNull": false,
          "autoincrement": false
        },
        "fatorPrograma": {
          "name": "fatorPrograma",
          "type": "decimal(12,7)",
          "primaryKey": false,
          "notNull": false,
          "autoincrement": false
        },
        "fatorAjuste": {
          "name": "fatorAjuste",
          "type": "decimal(12,7)",
          "primaryKey": false,
          "notNull": false,
          "autoincrement": false
        },
        "fatorInflacaoImplicita": {
          "name": "fatorInflacaoImplicita",
          "type": "decimal(12,7)",
          "primaryKey": false,
          "notNull": false,
          "autoincrement": false
        },
        "taxaJm": {
          "name": "taxaJm",
          "type": "decimal(8,4)",
          "primaryKey": false,
          "notNull": false,
          "autoincrement": false
        },
        "ipcaAcumulado": {
          "name": "ipcaAcumulado",
          "type": "decimal(8,4)",
          "primaryKey": false,
          "notNull": false,
          "autoincrement": false
        },
        "saldoDevedorAtualizado": {
          "name": "saldoDevedorAtualizado",
          "type": "decimal(18,2)",
          "primaryKey": false,
          "notNull": false,
          "autoincrement": false
        },
        "jurosRemuneratoriosCalculados": {
          "name": "jurosRemuneratoriosCalculados",
          "type": "decimal(18,2)",
          "primaryKey": false,
          "notNull": false,
          "autoincrement": false
        },
        "jurosMoraCalculados": {
          "name": "jurosMoraCalculados",
          "type": "decimal(18,2)",
          "primaryKey": false,
          "notNull": false,
          "autoincrement": false
        },
        "multaCalculada": {
          "name": "multaCalculada",
          "type": "decimal(18,2)",
          "primaryKey": false,
          "notNull": false,
          "autoincrement": false
        },
        "totalDevido": {
          "name": "totalDevido",
          "type": "decimal(18,2)",
          "primaryKey": false,
          "notNull": false,
          "autoincrement": false
        },
        "tcrEfetiva": {
          "name": "tcrEfetiva",
          "type": "decimal(8,4)",
          "primaryKey": false,
          "notNull": false,
          "autoincrement": false
        },
        "conformeLimiteRemuneratorios": {
          "name": "conformeLimiteRemuneratorios",
          "type": "enum('sim','nao','atencao')",
          "primaryKey": false,
          "notNull": false,
          "autoincrement": false,
          "default": "'sim'"
        },
        "conformeLimiteMora": {
          "name": "conformeLimiteMora",
          "type": "enum('sim','nao','atencao')",
          "primaryKey": false,
          "notNull": false,
          "autoincrement": false,
          "default": "'sim'"
        },
        "alertasConformidade": {
          "name": "alertasConformidade",
          "type": "text",
          "primaryKey": false,
          "notNull": false,
          "autoincrement": false
        },
        "memoriaCalculo": {
          "name": "memoriaCalculo",
          "type": "json",
          "primaryKey": false,
          "notNull": false,
          "autoincrement": false
        },
        "createdAt": {
          "name": "createdAt",
          "type": "timestamp",
          "primaryKey": false,
          "notNull": true,
          "autoincrement": false,
          "default": "(now())"
        },
        "updatedAt": {
          "name": "updatedAt",
          "type": "timestamp",
          "primaryKey": false,
          "notNull": true,
          "autoincrement": false,
          "onUpdate": true,
          "default": "(now())"
        }
      },
      "indexes": {},
      "foreignKeys": {},
      "compositePrimaryKeys": {
        "calculos_tcr_id": {
          "name": "calculos_tcr_id",
          "columns": [
            "id"
          ]
        }
      },
      "uniqueConstraints": {},
      "checkConstraint": {}
    },
    "contratos_cadeia": {
      "name": "contratos_cadeia",
      "columns": {
        "id": {
          "name": "id",
          "type": "int",
          "primaryKey": false,
          "notNull": true,
          "autoincrement": true
        },
        "cadeiaId": {
          "name": "cadeiaId",
          "type": "int",
          "primaryKey": false,
          "notNull": true,
          "autoincrement": false
        },
        "ordem": {
          "name": "ordem",
          "type": "int",
          "primaryKey": false,
          "notNull": true,
          "autoincrement": false
        },
        "tipo": {
          "name": "tipo",
          "type": "enum('original','aditivo','refinanciamento','novacao','renegociacao')",
          "primaryKey": false,
          "notNull": true,
          "autoincrement": false
        },
        "numeroContrato": {
          "name": "numeroContrato",
          "type": "varchar(100)",
          "primaryKey": false,
          "notNull": true,
          "autoincrement": false
        },
        "dataContratacao": {
          "name": "dataContratacao",
          "type": "varchar(20)",
          "primaryKey": false,
          "notNull": true,
          "autoincrement": false
        },
        "dataVencimento": {
          "name": "dataVencimento",
          "type": "varchar(20)",
          "primaryKey": false,
          "notNull": true,
          "autoincrement": false
        },
        "modalidade": {
          "name": "modalidade",
          "type": "enum('custeio','investimento','comercializacao','outro')",
          "primaryKey": false,
          "notNull": true,
          "autoincrement": false
        },
        "valorContrato": {
          "name": "valorContrato",
          "type": "decimal(18,2)",
          "primaryKey": false,
          "notNull": true,
          "autoincrement": false
        },
        "valorPrincipalOriginal": {
          "name": "valorPrincipalOriginal",
          "type": "decimal(18,2)",
          "primaryKey": false,
          "notNull": false,
          "autoincrement": false
        },
        "valorEncargosIncorporados": {
          "name": "valorEncargosIncorporados",
          "type": "decimal(18,2)",
          "primaryKey": false,
          "notNull": false,
          "autoincrement": false
        },
        "taxaJurosAnual": {
          "name": "taxaJurosAnual",
          "type": "decimal(8,4)",
          "primaryKey": false,
          "notNull": true,
          "autoincrement": false
        },
        "taxaJurosMora": {
          "name": "taxaJurosMora",
          "type": "decimal(8,4)",
          "primaryKey": false,
          "notNull": false,
          "autoincrement": false
        },
        "numeroParcelas": {
          "name": "numeroParcelas",
          "type": "int",
          "primaryKey": false,
          "notNull": false,
          "autoincrement": false
        },
        "sistemaAmortizacao": {
          "name": "sistemaAmortizacao",
          "type": "enum('price','sac','saf','outro')",
          "primaryKey": false,
          "notNull": false,
          "autoincrement": false
        },
        "garantias": {
          "name": "garantias",
          "type": "text",
          "primaryKey": false,
          "notNull": false,
          "autoincrement": false
        },
        "observacoes": {
          "name": "observacoes",
          "type": "text",
          "primaryKey": false,
          "notNull": false,
          "autoincrement": false
        },
        "alertasDetectados": {
          "name": "alertasDetectados",
          "type": "json",
          "primaryKey": false,
          "notNull": false,
          "autoincrement": false
        },
        "createdAt": {
          "name": "createdAt",
          "type": "timestamp",
          "primaryKey": false,
          "notNull": true,
          "autoincrement": false,
          "default": "(now())"
        }
      },
      "indexes": {},
      "foreignKeys": {},
      "compositePrimaryKeys": {
        "contratos_cadeia_id": {
          "name": "contratos_cadeia_id",
          "columns": [
            "id"
          ]
        }
      },
      "uniqueConstraints": {},
      "checkConstraint": {}
    },
    "perfil_advogado": {
      "name": "perfil_advogado",
      "columns": {
        "id": {
          "name": "id",
          "type": "int",
          "primaryKey": false,
          "notNull": true,
          "autoincrement": true
        },
        "userId": {
          "name": "userId",
          "type": "int",
          "primaryKey": false,
          "notNull": true,
          "autoincrement": false
        },
        "nome": {
          "name": "nome",
          "type": "varchar(255)",
          "primaryKey": false,
          "notNull": true,
          "autoincrement": false
        },
        "oab": {
          "name": "oab",
          "type": "varchar(30)",
          "primaryKey": false,
          "notNull": true,
          "autoincrement": false
        },
        "cpf": {
          "name": "cpf",
          "type": "varchar(14)",
          "primaryKey": false,
          "notNull": false,
          "autoincrement": false
        },
        "email": {
          "name": "email",
          "type": "varchar(320)",
          "primaryKey": false,
          "notNull": false,
          "autoincrement": false
        },
        "telefone": {
          "name": "telefone",
          "type": "varchar(20)",
          "primaryKey": false,
          "notNull": false,
          "autoincrement": false
        },
        "escritorio": {
          "name": "escritorio",
          "type": "varchar(255)",
          "primaryKey": false,
          "notNull": false,
          "autoincrement": false
        },
        "endereco": {
          "name": "endereco",
          "type": "varchar(255)",
          "primaryKey": false,
          "notNull": false,
          "autoincrement": false
        },
        "cidade": {
          "name": "cidade",
          "type": "varchar(100)",
          "primaryKey": false,
          "notNull": false,
          "autoincrement": false
        },
        "estado": {
          "name": "estado",
          "type": "varchar(2)",
          "primaryKey": false,
          "notNull": false,
          "autoincrement": false
        },
        "cep": {
          "name": "cep",
          "type": "varchar(9)",
          "primaryKey": false,
          "notNull": false,
          "autoincrement": false
        },
        "createdAt": {
          "name": "createdAt",
          "type": "timestamp",
          "primaryKey": false,
          "notNull": true,
          "autoincrement": false,
          "default": "(now())"
        },
        "updatedAt": {
          "name": "updatedAt",
          "type": "timestamp",
          "primaryKey": false,
          "notNull": true,
          "autoincrement": false,
          "onUpdate": true,
          "default": "(now())"
        }
      },
      "indexes": {},
      "foreignKeys": {},
      "compositePrimaryKeys": {
        "perfil_advogado_id": {
          "name": "perfil_advogado_id",
          "columns": [
            "id"
          ]
        }
      },
      "uniqueConstraints": {
        "perfil_advogado_userId_unique": {
          "name": "perfil_advogado_userId_unique",
          "columns": [
            "userId"
          ]
        }
      },
      "checkConstraint": {}
    },
    "perfil_perito": {
      "name": "perfil_perito",
      "columns": {
        "id": {
          "name": "id",
          "type": "int",
          "primaryKey": false,
          "notNull": true,
          "autoincrement": true
        },
        "userId": {
          "name": "userId",
          "type": "int",
          "primaryKey": false,
          "notNull": true,
          "autoincrement": false
        },
        "nome": {
          "name": "nome",
          "type": "varchar(255)",
          "primaryKey": false,
          "notNull": true,
          "autoincrement": false
        },
        "categoria": {
          "name": "categoria",
          "type": "enum('contador','economista','administrador','tecnico_contabil','outro')",
          "primaryKey": false,
          "notNull": true,
          "autoincrement": false
        },
        "registroProfissional": {
          "name": "registroProfissional",
          "type": "varchar(50)",
          "primaryKey": false,
          "notNull": true,
          "autoincrement": false
        },
        "cpf": {
          "name": "cpf",
          "type": "varchar(14)",
          "primaryKey": false,
          "notNull": false,
          "autoincrement": false
        },
        "email": {
          "name": "email",
          "type": "varchar(320)",
          "primaryKey": false,
          "notNull": false,
          "autoincrement": false
        },
        "telefone": {
          "name": "telefone",
          "type": "varchar(20)",
          "primaryKey": false,
          "notNull": false,
          "autoincrement": false
        },
        "empresa": {
          "name": "empresa",
          "type": "varchar(255)",
          "primaryKey": false,
          "notNull": false,
          "autoincrement": false
        },
        "endereco": {
          "name": "endereco",
          "type": "varchar(255)",
          "primaryKey": false,
          "notNull": false,
          "autoincrement": false
        },
        "cidade": {
          "name": "cidade",
          "type": "varchar(100)",
          "primaryKey": false,
          "notNull": false,
          "autoincrement": false
        },
        "estado": {
          "name": "estado",
          "type": "varchar(2)",
          "primaryKey": false,
          "notNull": false,
          "autoincrement": false
        },
        "cep": {
          "name": "cep",
          "type": "varchar(9)",
          "primaryKey": false,
          "notNull": false,
          "autoincrement": false
        },
        "createdAt": {
          "name": "createdAt",
          "type": "timestamp",
          "primaryKey": false,
          "notNull": true,
          "autoincrement": false,
          "default": "(now())"
        },
        "updatedAt": {
          "name": "updatedAt",
          "type": "timestamp",
          "primaryKey": false,
          "notNull": true,
          "autoincrement": false,
          "onUpdate": true,
          "default": "(now())"
        }
      },
      "indexes": {},
      "foreignKeys": {},
      "compositePrimaryKeys": {
        "perfil_perito_id": {
          "name": "perfil_perito_id",
          "columns": [
            "id"
          ]
        }
      },
      "uniqueConstraints": {
        "perfil_perito_userId_unique": {
          "name": "perfil_perito_userId_unique",
          "columns": [
            "userId"
          ]
        }
      },
      "checkConstraint": {}
    },
    "users": {
      "name": "users",
      "columns": {
        "id": {
          "name": "id",
          "type": "int",
          "primaryKey": false,
          "notNull": true,
          "autoincrement": true
        },
        "openId": {
          "name": "openId",
          "type": "varchar(64)",
          "primaryKey": false,
          "notNull": true,
          "autoincrement": false
        },
        "name": {
          "name": "name",
          "type": "text",
          "primaryKey": false,
          "notNull": false,
          "autoincrement": false
        },
        "email": {
          "name": "email",
          "type": "varchar(320)",
          "primaryKey": false,
          "notNull": false,
          "autoincrement": false
        },
        "loginMethod": {
          "name": "loginMethod",
          "type": "varchar(64)",
          "primaryKey": false,
          "notNull": false,
          "autoincrement": false
        },
        "role": {
          "name": "role",
          "type": "enum('user','admin')",
          "primaryKey": false,
          "notNull": true,
          "autoincrement": false,
          "default": "'user'"
        },
        "plano": {
          "name": "plano",
          "type": "enum('free','standard','premium','supreme','admin')",
          "primaryKey": false,
          "notNull": true,
          "autoincrement": false,
          "default": "'free'"
        },
        "planoExpiracao": {
          "name": "planoExpiracao",
          "type": "timestamp",
          "primaryKey": false,
          "notNull": false,
          "autoincrement": false
        },
        "calculosRealizados": {
          "name": "calculosRealizados",
          "type": "int",
          "primaryKey": false,
          "notNull": true,
          "autoincrement": false,
          "default": 0
        },
        "stripeCustomerId": {
          "name": "stripeCustomerId",
          "type": "varchar(128)",
          "primaryKey": false,
          "notNull": false,
          "autoincrement": false
        },
        "stripeSubscriptionId": {
          "name": "stripeSubscriptionId",
          "type": "varchar(128)",
          "primaryKey": false,
          "notNull": false,
          "autoincrement": false
        },
        "createdAt": {
          "name": "createdAt",
          "type": "timestamp",
          "primaryKey": false,
          "notNull": true,
          "autoincrement": false,
          "default": "(now())"
        },
        "updatedAt": {
          "name": "updatedAt",
          "type": "timestamp",
          "primaryKey": false,
          "notNull": true,
          "autoincrement": false,
          "onUpdate": true,
          "default": "(now())"
        },
        "lastSignedIn": {
          "name": "lastSignedIn",
          "type": "timestamp",
          "primaryKey": false,
          "notNull": true,
          "autoincrement": false,
          "default": "(now())"
        }
      },
      "indexes": {},
      "foreignKeys": {},
      "compositePrimaryKeys": {
        "users_id": {
          "name": "users_id",
          "columns": [
            "id"
          ]
        }
      },
      "uniqueConstraints": {
        "users_openId_unique": {
          "name": "users_openId_unique",
          "columns": [
            "openId"
          ]
        }
      },
      "checkConstraint": {}
    }
  },
  "views": {},
  "_meta": {
    "schemas": {},
    "tables": {},
    "columns": {}
  },
  "internal": {
    "tables": {},
    "indexes": {}
  }
}